.gitignore
.travis.yml
CHANGES.rst
MANIFEST.in
README.rst
default.nix
setup.py
travis.cfg
src/collective/__init__.py
src/collective.recipe.nix.egg-info/PKG-INFO
src/collective.recipe.nix.egg-info/SOURCES.txt
src/collective.recipe.nix.egg-info/dependency_links.txt
src/collective.recipe.nix.egg-info/entry_points.txt
src/collective.recipe.nix.egg-info/namespace_packages.txt
src/collective.recipe.nix.egg-info/not-zip-safe
src/collective.recipe.nix.egg-info/requires.txt
src/collective.recipe.nix.egg-info/top_level.txt
src/collective/recipe/__init__.py
src/collective/recipe/nix/__init__.py
src/collective/recipe/nix/cache.py