Metadata-Version: 1.1
Name: collective.recipe.nix
Version: 1.0.3
Summary: Buildout recipe for creating Nix expressions from eggs list
Home-page: https://github.com/datakurre/collective.recipe.nix/
Author: Asko Soukka
Author-email: asko.soukka@iki.fi
License: GPL
Platform: UNKNOWN
Classifier: Development Status :: 4 - Beta
Classifier: Framework :: Buildout :: Recipe
Classifier: Framework :: Buildout
Classifier: Programming Language :: Python :: 2.6
Classifier: Programming Language :: Python :: 2.7
Classifier: Programming Language :: Python :: 3.4
Classifier: Programming Language :: Python
